[
  {
    "name": "tablespace_space",
    "category": "oracle",
    "title": [
      "rac"
    ],
    "include": [["10.65.193.13","whlt"],["10.65.193.11","whpay"]],
    "version": ""
  },
  {
    "name": "invalid_object",
    "category": "oracle",
    "version": ""
  },
  {
    "name": "disk_space",
    "category": "os",
    "alert": {
      "name": "disk_space",
      "include": [["10.65.193.13","10.65.193.11"]]
    },
    "version": ""
  },
  {
    "name": "no_primary_key",
    "category": "oracle",
    "version": ""
  }
]